<?xml version = '1.0' encoding = 'UTF-8'?>
<TableProxySqlServerv2k5 class="oracle.dbtools.crest.model.design.storage.sqlserver.v2k5.TableProxySqlServerv2k5" name="BateriaCapacitacion" directorySegmentName="seg_0" id="5EE61BA3-7E9C-EDD7-B008-CC2347000501">
<createdBy>hucj1e3</createdBy>
<createdTime>2015-02-25 19:28:36 UTC</createdTime>
<generatorID>Generado por el Usuario</generatorID>
<ownerDesignName>DisIntervaRH</ownerDesignName>
<schemaObject>A6120FEA-43C4-FC97-382A-C4BC6897142C</schemaObject>
<database>D65A6732-1F55-5E38-6619-CEC0889DF99B</database>
<filegroup>7DAA336A-625C-F86E-A733-29B3C6994CFC</filegroup>
<schema>1</schema>
<columnProxies>
<ColumnProxy class="oracle.dbtools.crest.model.design.storage.sqlserver.v2k5.ColumnProxySqlServerv2k5" name="IdPuesto" id="36CC1919-FC8E-C643-50D7-A002D030B8A0">
<createdBy>hucj1e3</createdBy>
<createdTime>2015-02-25 19:28:36 UTC</createdTime>
<generatorID>Generado por el Usuario</generatorID>
<ownerDesignName>DisIntervaRH</ownerDesignName>
</ColumnProxy>
<ColumnProxy class="oracle.dbtools.crest.model.design.storage.sqlserver.v2k5.ColumnProxySqlServerv2k5" name="IdCursoCapacitacion" id="3D276990-96BD-2AAE-F4A7-F80BE40998BE">
<createdBy>hucj1e3</createdBy>
<createdTime>2015-02-25 19:28:36 UTC</createdTime>
<generatorID>Generado por el Usuario</generatorID>
<ownerDesignName>DisIntervaRH</ownerDesignName>
</ColumnProxy>
<ColumnProxy class="oracle.dbtools.crest.model.design.storage.sqlserver.v2k5.ColumnProxySqlServerv2k5" name="IdBateriaCapacitacion" id="729579CC-143A-0145-D6E8-489247D45983">
<createdBy>hucj1e3</createdBy>
<createdTime>2015-02-25 19:28:36 UTC</createdTime>
<generatorID>Generado por el Usuario</generatorID>
<ownerDesignName>DisIntervaRH</ownerDesignName>
</ColumnProxy>
<ColumnProxy class="oracle.dbtools.crest.model.design.storage.sqlserver.v2k5.ColumnProxySqlServerv2k5" name="Ponderacion" id="F4E12BDF-EB9E-752D-9741-2B04F41C7B16">
<createdBy>hucj1e3</createdBy>
<createdTime>2015-02-25 19:28:36 UTC</createdTime>
<generatorID>Generado por el Usuario</generatorID>
<ownerDesignName>DisIntervaRH</ownerDesignName>
</ColumnProxy>
</columnProxies>
<foreignKeys>
<ForeignKey class="oracle.dbtools.crest.model.design.storage.sqlserver.v2k5.FKProxySqlServerv2k5" name="FK_BateriaCapacitacion_CursosCapacitacion" id="F9877028-D9FF-0EB3-B0B0-245F15CA8A10">
<createdBy>hucj1e3</createdBy>
<createdTime>2015-02-25 19:28:37 UTC</createdTime>
<generatorID>Generado por el Usuario</generatorID>
<ownerDesignName>DisIntervaRH</ownerDesignName>
</ForeignKey>
<ForeignKey class="oracle.dbtools.crest.model.design.storage.sqlserver.v2k5.FKProxySqlServerv2k5" name="FK_BateriaCapacitacion_Puestos" id="FD3BC23F-C0F1-1180-D82D-B20A3BECC1DB">
<createdBy>hucj1e3</createdBy>
<createdTime>2015-02-25 19:28:37 UTC</createdTime>
<generatorID>Generado por el Usuario</generatorID>
<ownerDesignName>DisIntervaRH</ownerDesignName>
</ForeignKey>
</foreignKeys>
<primaryKeys>
<PrimaryKey class="oracle.dbtools.crest.model.design.storage.sqlserver.v2k5.PKProxySqlServerv2k5" name="PK_BateriaCapacitacion" id="1F3C2717-5A99-9E25-BBF9-CA819EB89F2D">
<createdBy>hucj1e3</createdBy>
<createdTime>2015-02-25 19:28:36 UTC</createdTime>
<generatorID>Generado por el Usuario</generatorID>
<ownerDesignName>DisIntervaRH</ownerDesignName>
<clustered>true</clustered>
<fileGroup>7DAA336A-625C-F86E-A733-29B3C6994CFC</fileGroup>
<recomputeStatistics>NO</recomputeStatistics>
</PrimaryKey>
</primaryKeys>
</TableProxySqlServerv2k5>